[
  {
    "Year": 2015,
    "Country": "Oman",
    "Continent": "Africa",
    "Happiness.Rank": 22,
    "Happiness.scores": 6.853,
    "GDP": 1.36011,
    "Social.support": 1.08182,
    "Helathy.life.expectancy": 0.76276,
    "Freedom.to.make.choices": 0.63274,
    "Generosity": 0.21542,
    "Perceptions.of.corruption": 0.32524
  },
  {
    "Year": 2015,
    "Country": "Taiwan",
    "Continent": "Africa",
    "Happiness.Rank": 38,
    "Happiness.scores": 6.298,
    "GDP": 1.29098,
    "Social.support": 1.07617,
    "Helathy.life.expectancy": 0.8753,
    "Freedom.to.make.choices": 0.3974,
    "Generosity": 0.25376,
    "Perceptions.of.corruption": 0.08129
  },
  {
    "Year": 2015,
    "Country": "Suriname",
    "Continent": "Africa",
    "Happiness.Rank": 40,
    "Happiness.scores": 6.269,
    "GDP": 0.99534,
    "Social.support": 0.972,
    "Helathy.life.expectancy": 0.6082,
    "Freedom.to.make.choices": 0.59657,
    "Generosity": 0.16991,
    "Perceptions.of.corruption": 0.13633
  },
  {
    "Year": 2015,
    "Country": "Libya",
    "Continent": "Africa",
    "Happiness.Rank": 63,
    "Happiness.scores": 5.754,
    "GDP": 1.13145,
    "Social.support": 1.11862,
    "Helathy.life.expectancy": 0.7038,
    "Freedom.to.make.choices": 0.41668,
    "Generosity": 0.18295,
    "Perceptions.of.corruption": 0.11023
  },
  {
    "Year": 2015,
    "Country": "Algeria",
    "Continent": "Africa",
    "Happiness.Rank": 68,
    "Happiness.scores": 5.605,
    "GDP": 0.93929,
    "Social.support": 1.07772,
    "Helathy.life.expectancy": 0.61766,
    "Freedom.to.make.choices": 0.28579,
    "Generosity": 0.07822,
    "Perceptions.of.corruption": 0.17383
  },
  {
    "Year": 2015,
    "Country": "Mauritius",
    "Continent": "Africa",
    "Happiness.Rank": 71,
    "Happiness.scores": 5.477,
    "GDP": 1.00761,
    "Social.support": 0.98521,
    "Helathy.life.expectancy": 0.7095,
    "Freedom.to.make.choices": 0.56066,
    "Generosity": 0.37744,
    "Perceptions.of.corruption": 0.07521
  },
  {
    "Year": 2015,
    "Country": "Hong Kong",
    "Continent": "Africa",
    "Happiness.Rank": 72,
    "Happiness.scores": 5.474,
    "GDP": 1.38604,
    "Social.support": 1.05818,
    "Helathy.life.expectancy": 1.01328,
    "Freedom.to.make.choices": 0.59608,
    "Generosity": 0.39478,
    "Perceptions.of.corruption": 0.37124
  },
  {
    "Year": 2015,
    "Country": "Nigeria",
    "Continent": "Africa",
    "Happiness.Rank": 78,
    "Happiness.scores": 5.268,
    "GDP": 0.65435,
    "Social.support": 0.90432,
    "Helathy.life.expectancy": 0.16007,
    "Freedom.to.make.choices": 0.34334,
    "Generosity": 0.27233,
    "Perceptions.of.corruption": 0.0403
  },
  {
    "Year": 2015,
    "Country": "Zambia",
    "Continent": "Africa",
    "Happiness.Rank": 85,
    "Happiness.scores": 5.129,
    "GDP": 0.47038,
    "Social.support": 0.91612,
    "Helathy.life.expectancy": 0.29924,
    "Freedom.to.make.choices": 0.48827,
    "Generosity": 0.19591,
    "Perceptions.of.corruption": 0.12468
  },
  {
    "Year": 2015,
    "Country": "Somaliland region",
    "Continent": "Africa",
    "Happiness.Rank": 91,
    "Happiness.scores": 5.057,
    "GDP": 0.18847,
    "Social.support": 0.95152,
    "Helathy.life.expectancy": 0.43873,
    "Freedom.to.make.choices": 0.46582,
    "Generosity": 0.50318,
    "Perceptions.of.corruption": 0.39928
  },
  {
    "Year": 2015,
    "Country": "Morocco",
    "Continent": "Africa",
    "Happiness.Rank": 92,
    "Happiness.scores": 5.013,
    "GDP": 0.73479,
    "Social.support": 0.64095,
    "Helathy.life.expectancy": 0.60954,
    "Freedom.to.make.choices": 0.41691,
    "Generosity": 0.07172,
    "Perceptions.of.corruption": 0.08546
  },
  {
    "Year": 2015,
    "Country": "Mozambique",
    "Continent": "Africa",
    "Happiness.Rank": 94,
    "Happiness.scores": 4.971,
    "GDP": 0.08308,
    "Social.support": 1.02626,
    "Helathy.life.expectancy": 0.09131,
    "Freedom.to.make.choices": 0.34037,
    "Generosity": 0.22269,
    "Perceptions.of.corruption": 0.15603
  },
  {
    "Year": 2015,
    "Country": "Lesotho",
    "Continent": "Africa",
    "Happiness.Rank": 97,
    "Happiness.scores": 4.898,
    "GDP": 0.37545,
    "Social.support": 1.04103,
    "Helathy.life.expectancy": 0.07612,
    "Freedom.to.make.choices": 0.31767,
    "Generosity": 0.16388,
    "Perceptions.of.corruption": 0.12504
  },
  {
    "Year": 2015,
    "Country": "Laos",
    "Continent": "Africa",
    "Happiness.Rank": 99,
    "Happiness.scores": 4.876,
    "GDP": 0.59066,
    "Social.support": 0.73803,
    "Helathy.life.expectancy": 0.54909,
    "Freedom.to.make.choices": 0.59591,
    "Generosity": 0.42192,
    "Perceptions.of.corruption": 0.24249
  },
  {
    "Year": 2015,
    "Country": "Swaziland",
    "Continent": "Africa",
    "Happiness.Rank": 101,
    "Happiness.scores": 4.867,
    "GDP": 0.71206,
    "Social.support": 1.07284,
    "Helathy.life.expectancy": 0.07566,
    "Freedom.to.make.choices": 0.30658,
    "Generosity": 0.18259,
    "Perceptions.of.corruption": 0.0306
  },
  {
    "Year": 2015,
    "Country": "Tunisia",
    "Continent": "Africa",
    "Happiness.Rank": 107,
    "Happiness.scores": 4.739,
    "GDP": 0.88113,
    "Social.support": 0.60429,
    "Helathy.life.expectancy": 0.73793,
    "Freedom.to.make.choices": 0.26268,
    "Generosity": 0.06431,
    "Perceptions.of.corruption": 0.06358
  },
  {
    "Year": 2015,
    "Country": "South Africa",
    "Continent": "Africa",
    "Happiness.Rank": 113,
    "Happiness.scores": 4.642,
    "GDP": 0.92049,
    "Social.support": 1.18468,
    "Helathy.life.expectancy": 0.27688,
    "Freedom.to.make.choices": 0.33207,
    "Generosity": 0.11973,
    "Perceptions.of.corruption": 0.08884
  },
  {
    "Year": 2015,
    "Country": "Ghana",
    "Continent": "Africa",
    "Happiness.Rank": 114,
    "Happiness.scores": 4.633,
    "GDP": 0.54558,
    "Social.support": 0.67954,
    "Helathy.life.expectancy": 0.40132,
    "Freedom.to.make.choices": 0.42342,
    "Generosity": 0.23087,
    "Perceptions.of.corruption": 0.04355
  },
  {
    "Year": 2015,
    "Country": "Zimbabwe",
    "Continent": "Africa",
    "Happiness.Rank": 115,
    "Happiness.scores": 4.61,
    "GDP": 0.271,
    "Social.support": 1.03276,
    "Helathy.life.expectancy": 0.33475,
    "Freedom.to.make.choices": 0.25861,
    "Generosity": 0.18987,
    "Perceptions.of.corruption": 0.08079
  },
  {
    "Year": 2015,
    "Country": "Liberia",
    "Continent": "Africa",
    "Happiness.Rank": 116,
    "Happiness.scores": 4.571,
    "GDP": 0.0712,
    "Social.support": 0.78968,
    "Helathy.life.expectancy": 0.34201,
    "Freedom.to.make.choices": 0.28531,
    "Generosity": 0.24362,
    "Perceptions.of.corruption": 0.06232
  },
  {
    "Year": 2015,
    "Country": "Sudan",
    "Continent": "Africa",
    "Happiness.Rank": 118,
    "Happiness.scores": 4.55,
    "GDP": 0.52107,
    "Social.support": 1.01404,
    "Helathy.life.expectancy": 0.36878,
    "Freedom.to.make.choices": 0.10081,
    "Generosity": 0.19062,
    "Perceptions.of.corruption": 0.1466
  },
  {
    "Year": 2015,
    "Country": "Congo (Kinshasa)",
    "Continent": "Africa",
    "Happiness.Rank": 120,
    "Happiness.scores": 4.517,
    "GDP": 0,
    "Social.support": 1.0012,
    "Helathy.life.expectancy": 0.09806,
    "Freedom.to.make.choices": 0.22605,
    "Generosity": 0.24834,
    "Perceptions.of.corruption": 0.07625
  },
  {
    "Year": 2015,
    "Country": "Ethiopia",
    "Continent": "Africa",
    "Happiness.Rank": 122,
    "Happiness.scores": 4.512,
    "GDP": 0.19073,
    "Social.support": 0.60406,
    "Helathy.life.expectancy": 0.44055,
    "Freedom.to.make.choices": 0.4345,
    "Generosity": 0.24325,
    "Perceptions.of.corruption": 0.15048
  },
  {
    "Year": 2015,
    "Country": "Sierra Leone",
    "Continent": "Africa",
    "Happiness.Rank": 123,
    "Happiness.scores": 4.507,
    "GDP": 0.33024,
    "Social.support": 0.95571,
    "Helathy.life.expectancy": 0,
    "Freedom.to.make.choices": 0.4084,
    "Generosity": 0.21488,
    "Perceptions.of.corruption": 0.08786
  },
  {
    "Year": 2015,
    "Country": "Mauritania",
    "Continent": "Africa",
    "Happiness.Rank": 124,
    "Happiness.scores": 4.436,
    "GDP": 0.45407,
    "Social.support": 0.86908,
    "Helathy.life.expectancy": 0.35874,
    "Freedom.to.make.choices": 0.24232,
    "Generosity": 0.219,
    "Perceptions.of.corruption": 0.17461
  },
  {
    "Year": 2015,
    "Country": "Kenya",
    "Continent": "Africa",
    "Happiness.Rank": 125,
    "Happiness.scores": 4.419,
    "GDP": 0.36471,
    "Social.support": 0.99876,
    "Helathy.life.expectancy": 0.41435,
    "Freedom.to.make.choices": 0.42215,
    "Generosity": 0.37542,
    "Perceptions.of.corruption": 0.05839
  },
  {
    "Year": 2015,
    "Country": "Djibouti",
    "Continent": "Africa",
    "Happiness.Rank": 126,
    "Happiness.scores": 4.369,
    "GDP": 0.44025,
    "Social.support": 0.59207,
    "Helathy.life.expectancy": 0.36291,
    "Freedom.to.make.choices": 0.46074,
    "Generosity": 0.18093,
    "Perceptions.of.corruption": 0.28105
  },
  {
    "Year": 2015,
    "Country": "Botswana",
    "Continent": "Africa",
    "Happiness.Rank": 128,
    "Happiness.scores": 4.332,
    "GDP": 0.99355,
    "Social.support": 1.10464,
    "Helathy.life.expectancy": 0.04776,
    "Freedom.to.make.choices": 0.49495,
    "Generosity": 0.10461,
    "Perceptions.of.corruption": 0.12474
  },
  {
    "Year": 2015,
    "Country": "Malawi",
    "Continent": "Africa",
    "Happiness.Rank": 131,
    "Happiness.scores": 4.292,
    "GDP": 0.01604,
    "Social.support": 0.41134,
    "Helathy.life.expectancy": 0.22562,
    "Freedom.to.make.choices": 0.43054,
    "Generosity": 0.33128,
    "Perceptions.of.corruption": 0.06977
  },
  {
    "Year": 2015,
    "Country": "Cameroon",
    "Continent": "Africa",
    "Happiness.Rank": 133,
    "Happiness.scores": 4.252,
    "GDP": 0.4225,
    "Social.support": 0.88767,
    "Helathy.life.expectancy": 0.23402,
    "Freedom.to.make.choices": 0.49309,
    "Generosity": 0.20618,
    "Perceptions.of.corruption": 0.05786
  },
  {
    "Year": 2015,
    "Country": "Egypt",
    "Continent": "Africa",
    "Happiness.Rank": 135,
    "Happiness.scores": 4.194,
    "GDP": 0.8818,
    "Social.support": 0.747,
    "Helathy.life.expectancy": 0.61712,
    "Freedom.to.make.choices": 0.17288,
    "Generosity": 0.11291,
    "Perceptions.of.corruption": 0.06324
  },
  {
    "Year": 2015,
    "Country": "Angola",
    "Continent": "Africa",
    "Happiness.Rank": 137,
    "Happiness.scores": 4.033,
    "GDP": 0.75778,
    "Social.support": 0.8604,
    "Helathy.life.expectancy": 0.16683,
    "Freedom.to.make.choices": 0.10384,
    "Generosity": 0.12344,
    "Perceptions.of.corruption": 0.07122
  },
  {
    "Year": 2015,
    "Country": "Mali",
    "Continent": "Africa",
    "Happiness.Rank": 138,
    "Happiness.scores": 3.995,
    "GDP": 0.26074,
    "Social.support": 1.03526,
    "Helathy.life.expectancy": 0.20583,
    "Freedom.to.make.choices": 0.38857,
    "Generosity": 0.18798,
    "Perceptions.of.corruption": 0.12352
  },
  {
    "Year": 2015,
    "Country": "Congo (Brazzaville)",
    "Continent": "Africa",
    "Happiness.Rank": 139,
    "Happiness.scores": 3.989,
    "GDP": 0.67866,
    "Social.support": 0.6629,
    "Helathy.life.expectancy": 0.31051,
    "Freedom.to.make.choices": 0.41466,
    "Generosity": 0.12388,
    "Perceptions.of.corruption": 0.11686
  },
  {
    "Year": 2015,
    "Country": "Comoros",
    "Continent": "Africa",
    "Happiness.Rank": 140,
    "Happiness.scores": 3.956,
    "GDP": 0.23906,
    "Social.support": 0.79273,
    "Helathy.life.expectancy": 0.36315,
    "Freedom.to.make.choices": 0.22917,
    "Generosity": 0.17441,
    "Perceptions.of.corruption": 0.199
  },
  {
    "Year": 2015,
    "Country": "Uganda",
    "Continent": "Africa",
    "Happiness.Rank": 141,
    "Happiness.scores": 3.931,
    "GDP": 0.21102,
    "Social.support": 1.13299,
    "Helathy.life.expectancy": 0.33861,
    "Freedom.to.make.choices": 0.45727,
    "Generosity": 0.29066,
    "Perceptions.of.corruption": 0.07267
  },
  {
    "Year": 2015,
    "Country": "Senegal",
    "Continent": "Africa",
    "Happiness.Rank": 142,
    "Happiness.scores": 3.904,
    "GDP": 0.36498,
    "Social.support": 0.97619,
    "Helathy.life.expectancy": 0.4354,
    "Freedom.to.make.choices": 0.36772,
    "Generosity": 0.20843,
    "Perceptions.of.corruption": 0.10713
  },
  {
    "Year": 2015,
    "Country": "Gabon",
    "Continent": "Africa",
    "Happiness.Rank": 143,
    "Happiness.scores": 3.896,
    "GDP": 1.06024,
    "Social.support": 0.90528,
    "Helathy.life.expectancy": 0.43372,
    "Freedom.to.make.choices": 0.31914,
    "Generosity": 0.06822,
    "Perceptions.of.corruption": 0.11091
  },
  {
    "Year": 2015,
    "Country": "Niger",
    "Continent": "Africa",
    "Happiness.Rank": 144,
    "Happiness.scores": 3.845,
    "GDP": 0.0694,
    "Social.support": 0.77265,
    "Helathy.life.expectancy": 0.29707,
    "Freedom.to.make.choices": 0.47692,
    "Generosity": 0.19387,
    "Perceptions.of.corruption": 0.15639
  },
  {
    "Year": 2015,
    "Country": "Tanzania",
    "Continent": "Africa",
    "Happiness.Rank": 146,
    "Happiness.scores": 3.781,
    "GDP": 0.2852,
    "Social.support": 1.00268,
    "Helathy.life.expectancy": 0.38215,
    "Freedom.to.make.choices": 0.32878,
    "Generosity": 0.34377,
    "Perceptions.of.corruption": 0.05747
  },
  {
    "Year": 2015,
    "Country": "Madagascar",
    "Continent": "Africa",
    "Happiness.Rank": 147,
    "Happiness.scores": 3.681,
    "GDP": 0.20824,
    "Social.support": 0.66801,
    "Helathy.life.expectancy": 0.46721,
    "Freedom.to.make.choices": 0.19184,
    "Generosity": 0.21333,
    "Perceptions.of.corruption": 0.08124
  },
  {
    "Year": 2015,
    "Country": "Central African Republic",
    "Continent": "Africa",
    "Happiness.Rank": 148,
    "Happiness.scores": 3.678,
    "GDP": 0.0785,
    "Social.support": 0,
    "Helathy.life.expectancy": 0.06699,
    "Freedom.to.make.choices": 0.48879,
    "Generosity": 0.23835,
    "Perceptions.of.corruption": 0.08289
  },
  {
    "Year": 2015,
    "Country": "Chad",
    "Continent": "Africa",
    "Happiness.Rank": 149,
    "Happiness.scores": 3.667,
    "GDP": 0.34193,
    "Social.support": 0.76062,
    "Helathy.life.expectancy": 0.1501,
    "Freedom.to.make.choices": 0.23501,
    "Generosity": 0.18386,
    "Perceptions.of.corruption": 0.05269
  },
  {
    "Year": 2015,
    "Country": "Guinea",
    "Continent": "Africa",
    "Happiness.Rank": 150,
    "Happiness.scores": 3.656,
    "GDP": 0.17417,
    "Social.support": 0.46475,
    "Helathy.life.expectancy": 0.24009,
    "Freedom.to.make.choices": 0.37725,
    "Generosity": 0.28657,
    "Perceptions.of.corruption": 0.12139
  },
  {
    "Year": 2015,
    "Country": "Ivory Coast",
    "Continent": "Africa",
    "Happiness.Rank": 151,
    "Happiness.scores": 3.655,
    "GDP": 0.46534,
    "Social.support": 0.77115,
    "Helathy.life.expectancy": 0.15185,
    "Freedom.to.make.choices": 0.46866,
    "Generosity": 0.20165,
    "Perceptions.of.corruption": 0.17922
  },
  {
    "Year": 2015,
    "Country": "Burkina Faso",
    "Continent": "Africa",
    "Happiness.Rank": 152,
    "Happiness.scores": 3.587,
    "GDP": 0.25812,
    "Social.support": 0.85188,
    "Helathy.life.expectancy": 0.27125,
    "Freedom.to.make.choices": 0.39493,
    "Generosity": 0.21747,
    "Perceptions.of.corruption": 0.12832
  },
  {
    "Year": 2015,
    "Country": "Rwanda",
    "Continent": "Africa",
    "Happiness.Rank": 154,
    "Happiness.scores": 3.465,
    "GDP": 0.22208,
    "Social.support": 0.7737,
    "Helathy.life.expectancy": 0.42864,
    "Freedom.to.make.choices": 0.59201,
    "Generosity": 0.22628,
    "Perceptions.of.corruption": 0.55191
  },
  {
    "Year": 2015,
    "Country": "Benin",
    "Continent": "Africa",
    "Happiness.Rank": 155,
    "Happiness.scores": 3.34,
    "GDP": 0.28665,
    "Social.support": 0.35386,
    "Helathy.life.expectancy": 0.3191,
    "Freedom.to.make.choices": 0.4845,
    "Generosity": 0.1826,
    "Perceptions.of.corruption": 0.0801
  },
  {
    "Year": 2015,
    "Country": "Burundi",
    "Continent": "Africa",
    "Happiness.Rank": 157,
    "Happiness.scores": 2.905,
    "GDP": 0.0153,
    "Social.support": 0.41587,
    "Helathy.life.expectancy": 0.22396,
    "Freedom.to.make.choices": 0.1185,
    "Generosity": 0.19727,
    "Perceptions.of.corruption": 0.10062
  },
  {
    "Year": 2015,
    "Country": "Togo",
    "Continent": "Africa",
    "Happiness.Rank": 158,
    "Happiness.scores": 2.839,
    "GDP": 0.20868,
    "Social.support": 0.13995,
    "Helathy.life.expectancy": 0.28443,
    "Freedom.to.make.choices": 0.36453,
    "Generosity": 0.16681,
    "Perceptions.of.corruption": 0.10731
  },
  {
    "Year": 2018,
    "Country": "United States of America",
    "Continent": "Africa",
    "Happiness.Rank": 19,
    "Happiness.scores": 6.892,
    "GDP": 1.433,
    "Social.support": 1.457,
    "Helathy.life.expectancy": 0.874,
    "Freedom.to.make.choices": 0.454,
    "Generosity": 0.28,
    "Perceptions.of.corruption": 0.128
  },
  {
    "Year": 2018,
    "Country": "Taiwan",
    "Continent": "Africa",
    "Happiness.Rank": 25,
    "Happiness.scores": 6.446,
    "GDP": 1.368,
    "Social.support": 1.43,
    "Helathy.life.expectancy": 0.914,
    "Freedom.to.make.choices": 0.351,
    "Generosity": 0.242,
    "Perceptions.of.corruption": 0.097
  },
  {
    "Year": 2018,
    "Country": "Trinidad & Tobago",
    "Continent": "Africa",
    "Happiness.Rank": 39,
    "Happiness.scores": 6.192,
    "GDP": 1.231,
    "Social.support": 1.477,
    "Helathy.life.expectancy": 0.713,
    "Freedom.to.make.choices": 0.489,
    "Generosity": 0.185,
    "Perceptions.of.corruption": 0.016
  },
  {
    "Year": 2018,
    "Country": "Mauritius",
    "Continent": "Africa",
    "Happiness.Rank": 57,
    "Happiness.scores": 5.888,
    "GDP": 1.12,
    "Social.support": 1.402,
    "Helathy.life.expectancy": 0.798,
    "Freedom.to.make.choices": 0.498,
    "Generosity": 0.215,
    "Perceptions.of.corruption": 0.06
  },
  {
    "Year": 2018,
    "Country": "Northern Cyprus",
    "Continent": "Africa",
    "Happiness.Rank": 64,
    "Happiness.scores": 5.718,
    "GDP": 1.263,
    "Social.support": 1.252,
    "Helathy.life.expectancy": 1.042,
    "Freedom.to.make.choices": 0.417,
    "Generosity": 0.191,
    "Perceptions.of.corruption": 0.162
  },
  {
    "Year": 2018,
    "Country": "Libya",
    "Continent": "Africa",
    "Happiness.Rank": 72,
    "Happiness.scores": 5.525,
    "GDP": 1.044,
    "Social.support": 1.303,
    "Helathy.life.expectancy": 0.673,
    "Freedom.to.make.choices": 0.416,
    "Generosity": 0.133,
    "Perceptions.of.corruption": 0.152
  },
  {
    "Year": 2018,
    "Country": "Hong Kong",
    "Continent": "Africa",
    "Happiness.Rank": 76,
    "Happiness.scores": 5.43,
    "GDP": 1.438,
    "Social.support": 1.277,
    "Helathy.life.expectancy": 1.122,
    "Freedom.to.make.choices": 0.44,
    "Generosity": 0.258,
    "Perceptions.of.corruption": 0.287
  },
  {
    "Year": 2018,
    "Country": "North Macedonia",
    "Continent": "Africa",
    "Happiness.Rank": 84,
    "Happiness.scores": 5.274,
    "GDP": 0.983,
    "Social.support": 1.294,
    "Helathy.life.expectancy": 0.838,
    "Freedom.to.make.choices": 0.345,
    "Generosity": 0.185,
    "Perceptions.of.corruption": 0.034
  },
  {
    "Year": 2018,
    "Country": "Nigeria",
    "Continent": "Africa",
    "Happiness.Rank": 85,
    "Happiness.scores": 5.265,
    "GDP": 0.696,
    "Social.support": 1.111,
    "Helathy.life.expectancy": 0.245,
    "Freedom.to.make.choices": 0.426,
    "Generosity": 0.215,
    "Perceptions.of.corruption": 0.041
  },
  {
    "Year": 2018,
    "Country": "Algeria",
    "Continent": "Africa",
    "Happiness.Rank": 88,
    "Happiness.scores": 5.211,
    "GDP": 1.002,
    "Social.support": 1.16,
    "Helathy.life.expectancy": 0.785,
    "Freedom.to.make.choices": 0.086,
    "Generosity": 0.073,
    "Perceptions.of.corruption": 0.114
  },
  {
    "Year": 2018,
    "Country": "Morocco",
    "Continent": "Africa",
    "Happiness.Rank": 89,
    "Happiness.scores": 5.208,
    "GDP": 0.801,
    "Social.support": 0.782,
    "Helathy.life.expectancy": 0.782,
    "Freedom.to.make.choices": 0.418,
    "Generosity": 0.036,
    "Perceptions.of.corruption": 0.076
  },
  {
    "Year": 2018,
    "Country": "Cameroon",
    "Continent": "Africa",
    "Happiness.Rank": 96,
    "Happiness.scores": 5.044,
    "GDP": 0.549,
    "Social.support": 0.91,
    "Helathy.life.expectancy": 0.331,
    "Freedom.to.make.choices": 0.381,
    "Generosity": 0.187,
    "Perceptions.of.corruption": 0.037
  },
  {
    "Year": 2018,
    "Country": "Ghana",
    "Continent": "Africa",
    "Happiness.Rank": 98,
    "Happiness.scores": 4.996,
    "GDP": 0.611,
    "Social.support": 0.868,
    "Helathy.life.expectancy": 0.486,
    "Freedom.to.make.choices": 0.381,
    "Generosity": 0.245,
    "Perceptions.of.corruption": 0.04
  },
  {
    "Year": 2018,
    "Country": "Ivory Coast",
    "Continent": "Africa",
    "Happiness.Rank": 99,
    "Happiness.scores": 4.944,
    "GDP": 0.569,
    "Social.support": 0.808,
    "Helathy.life.expectancy": 0.232,
    "Freedom.to.make.choices": 0.352,
    "Generosity": 0.154,
    "Perceptions.of.corruption": 0.09
  },
  {
    "Year": 2018,
    "Country": "Benin",
    "Continent": "Africa",
    "Happiness.Rank": 102,
    "Happiness.scores": 4.883,
    "GDP": 0.393,
    "Social.support": 0.437,
    "Helathy.life.expectancy": 0.397,
    "Freedom.to.make.choices": 0.349,
    "Generosity": 0.175,
    "Perceptions.of.corruption": 0.082
  },
  {
    "Year": 2018,
    "Country": "Congo (Brazzaville)",
    "Continent": "Africa",
    "Happiness.Rank": 103,
    "Happiness.scores": 4.812,
    "GDP": 0.673,
    "Social.support": 0.799,
    "Helathy.life.expectancy": 0.508,
    "Freedom.to.make.choices": 0.372,
    "Generosity": 0.105,
    "Perceptions.of.corruption": 0.093
  },
  {
    "Year": 2018,
    "Country": "Gabon",
    "Continent": "Africa",
    "Happiness.Rank": 104,
    "Happiness.scores": 4.799,
    "GDP": 1.057,
    "Social.support": 1.183,
    "Helathy.life.expectancy": 0.571,
    "Freedom.to.make.choices": 0.295,
    "Generosity": 0.043,
    "Perceptions.of.corruption": 0.055
  },
  {
    "Year": 2018,
    "Country": "Laos",
    "Continent": "Africa",
    "Happiness.Rank": 105,
    "Happiness.scores": 4.796,
    "GDP": 0.764,
    "Social.support": 1.03,
    "Helathy.life.expectancy": 0.551,
    "Freedom.to.make.choices": 0.547,
    "Generosity": 0.266,
    "Perceptions.of.corruption": 0.164
  },
  {
    "Year": 2018,
    "Country": "South Africa",
    "Continent": "Africa",
    "Happiness.Rank": 106,
    "Happiness.scores": 4.722,
    "GDP": 0.96,
    "Social.support": 1.351,
    "Helathy.life.expectancy": 0.469,
    "Freedom.to.make.choices": 0.389,
    "Generosity": 0.13,
    "Perceptions.of.corruption": 0.055
  },
  {
    "Year": 2018,
    "Country": "Senegal",
    "Continent": "Africa",
    "Happiness.Rank": 111,
    "Happiness.scores": 4.681,
    "GDP": 0.45,
    "Social.support": 1.134,
    "Helathy.life.expectancy": 0.571,
    "Freedom.to.make.choices": 0.292,
    "Generosity": 0.153,
    "Perceptions.of.corruption": 0.072
  },
  {
    "Year": 2018,
    "Country": "Somalia",
    "Continent": "Africa",
    "Happiness.Rank": 112,
    "Happiness.scores": 4.668,
    "GDP": 0,
    "Social.support": 0.698,
    "Helathy.life.expectancy": 0.268,
    "Freedom.to.make.choices": 0.559,
    "Generosity": 0.243,
    "Perceptions.of.corruption": 0.27
  },
  {
    "Year": 2018,
    "Country": "Namibia",
    "Continent": "Africa",
    "Happiness.Rank": 113,
    "Happiness.scores": 4.639,
    "GDP": 0.879,
    "Social.support": 1.313,
    "Helathy.life.expectancy": 0.477,
    "Freedom.to.make.choices": 0.401,
    "Generosity": 0.07,
    "Perceptions.of.corruption": 0.056
  },
  {
    "Year": 2018,
    "Country": "Niger",
    "Continent": "Africa",
    "Happiness.Rank": 114,
    "Happiness.scores": 4.628,
    "GDP": 0.138,
    "Social.support": 0.774,
    "Helathy.life.expectancy": 0.366,
    "Freedom.to.make.choices": 0.318,
    "Generosity": 0.188,
    "Perceptions.of.corruption": 0.102
  },
  {
    "Year": 2018,
    "Country": "Burkina Faso",
    "Continent": "Africa",
    "Happiness.Rank": 115,
    "Happiness.scores": 4.587,
    "GDP": 0.331,
    "Social.support": 1.056,
    "Helathy.life.expectancy": 0.38,
    "Freedom.to.make.choices": 0.255,
    "Generosity": 0.177,
    "Perceptions.of.corruption": 0.113
  },
  {
    "Year": 2018,
    "Country": "Guinea",
    "Continent": "Africa",
    "Happiness.Rank": 118,
    "Happiness.scores": 4.534,
    "GDP": 0.38,
    "Social.support": 0.829,
    "Helathy.life.expectancy": 0.375,
    "Freedom.to.make.choices": 0.332,
    "Generosity": 0.207,
    "Perceptions.of.corruption": 0.086
  },
  {
    "Year": 2018,
    "Country": "Gambia",
    "Continent": "Africa",
    "Happiness.Rank": 120,
    "Happiness.scores": 4.516,
    "GDP": 0.308,
    "Social.support": 0.939,
    "Helathy.life.expectancy": 0.428,
    "Freedom.to.make.choices": 0.382,
    "Generosity": 0.269,
    "Perceptions.of.corruption": 0.167
  },
  {
    "Year": 2018,
    "Country": "Kenya",
    "Continent": "Africa",
    "Happiness.Rank": 121,
    "Happiness.scores": 4.509,
    "GDP": 0.512,
    "Social.support": 0.983,
    "Helathy.life.expectancy": 0.581,
    "Freedom.to.make.choices": 0.431,
    "Generosity": 0.372,
    "Perceptions.of.corruption": 0.053
  },
  {
    "Year": 2018,
    "Country": "Mauritania",
    "Continent": "Africa",
    "Happiness.Rank": 122,
    "Happiness.scores": 4.49,
    "GDP": 0.57,
    "Social.support": 1.167,
    "Helathy.life.expectancy": 0.489,
    "Freedom.to.make.choices": 0.066,
    "Generosity": 0.106,
    "Perceptions.of.corruption": 0.088
  },
  {
    "Year": 2018,
    "Country": "Mozambique",
    "Continent": "Africa",
    "Happiness.Rank": 123,
    "Happiness.scores": 4.466,
    "GDP": 0.204,
    "Social.support": 0.986,
    "Helathy.life.expectancy": 0.39,
    "Freedom.to.make.choices": 0.494,
    "Generosity": 0.197,
    "Perceptions.of.corruption": 0.138
  },
  {
    "Year": 2018,
    "Country": "Tunisia",
    "Continent": "Africa",
    "Happiness.Rank": 124,
    "Happiness.scores": 4.461,
    "GDP": 0.921,
    "Social.support": 1,
    "Helathy.life.expectancy": 0.815,
    "Freedom.to.make.choices": 0.167,
    "Generosity": 0.059,
    "Perceptions.of.corruption": 0.055
  },
  {
    "Year": 2018,
    "Country": "Congo (Kinshasa)",
    "Continent": "Africa",
    "Happiness.Rank": 127,
    "Happiness.scores": 4.418,
    "GDP": 0.094,
    "Social.support": 1.125,
    "Helathy.life.expectancy": 0.357,
    "Freedom.to.make.choices": 0.269,
    "Generosity": 0.212,
    "Perceptions.of.corruption": 0.053
  },
  {
    "Year": 2018,
    "Country": "Mali",
    "Continent": "Africa",
    "Happiness.Rank": 128,
    "Happiness.scores": 4.39,
    "GDP": 0.385,
    "Social.support": 1.105,
    "Helathy.life.expectancy": 0.308,
    "Freedom.to.make.choices": 0.327,
    "Generosity": 0.153,
    "Perceptions.of.corruption": 0.052
  },
  {
    "Year": 2018,
    "Country": "Sierra Leone",
    "Continent": "Africa",
    "Happiness.Rank": 129,
    "Happiness.scores": 4.374,
    "GDP": 0.268,
    "Social.support": 0.841,
    "Helathy.life.expectancy": 0.242,
    "Freedom.to.make.choices": 0.309,
    "Generosity": 0.252,
    "Perceptions.of.corruption": 0.045
  },
  {
    "Year": 2018,
    "Country": "Chad",
    "Continent": "Africa",
    "Happiness.Rank": 132,
    "Happiness.scores": 4.35,
    "GDP": 0.35,
    "Social.support": 0.766,
    "Helathy.life.expectancy": 0.192,
    "Freedom.to.make.choices": 0.174,
    "Generosity": 0.198,
    "Perceptions.of.corruption": 0.078
  },
  {
    "Year": 2018,
    "Country": "Ethiopia",
    "Continent": "Africa",
    "Happiness.Rank": 134,
    "Happiness.scores": 4.286,
    "GDP": 0.336,
    "Social.support": 1.033,
    "Helathy.life.expectancy": 0.532,
    "Freedom.to.make.choices": 0.344,
    "Generosity": 0.209,
    "Perceptions.of.corruption": 0.1
  },
  {
    "Year": 2018,
    "Country": "Eswatini",
    "Continent": "Africa",
    "Happiness.Rank": 135,
    "Happiness.scores": 4.212,
    "GDP": 0.811,
    "Social.support": 1.149,
    "Helathy.life.expectancy": 0,
    "Freedom.to.make.choices": 0.313,
    "Generosity": 0.074,
    "Perceptions.of.corruption": 0.135
  },
  {
    "Year": 2018,
    "Country": "Uganda",
    "Continent": "Africa",
    "Happiness.Rank": 136,
    "Happiness.scores": 4.189,
    "GDP": 0.332,
    "Social.support": 1.069,
    "Helathy.life.expectancy": 0.443,
    "Freedom.to.make.choices": 0.356,
    "Generosity": 0.252,
    "Perceptions.of.corruption": 0.06
  },
  {
    "Year": 2018,
    "Country": "Egypt",
    "Continent": "Africa",
    "Happiness.Rank": 137,
    "Happiness.scores": 4.166,
    "GDP": 0.913,
    "Social.support": 1.039,
    "Helathy.life.expectancy": 0.644,
    "Freedom.to.make.choices": 0.241,
    "Generosity": 0.076,
    "Perceptions.of.corruption": 0.067
  },
  {
    "Year": 2018,
    "Country": "Zambia",
    "Continent": "Africa",
    "Happiness.Rank": 138,
    "Happiness.scores": 4.107,
    "GDP": 0.578,
    "Social.support": 1.058,
    "Helathy.life.expectancy": 0.426,
    "Freedom.to.make.choices": 0.431,
    "Generosity": 0.247,
    "Perceptions.of.corruption": 0.087
  },
  {
    "Year": 2018,
    "Country": "Togo",
    "Continent": "Africa",
    "Happiness.Rank": 139,
    "Happiness.scores": 4.085,
    "GDP": 0.275,
    "Social.support": 0.572,
    "Helathy.life.expectancy": 0.41,
    "Freedom.to.make.choices": 0.293,
    "Generosity": 0.177,
    "Perceptions.of.corruption": 0.085
  },
  {
    "Year": 2018,
    "Country": "Liberia",
    "Continent": "Africa",
    "Happiness.Rank": 141,
    "Happiness.scores": 3.975,
    "GDP": 0.073,
    "Social.support": 0.922,
    "Helathy.life.expectancy": 0.443,
    "Freedom.to.make.choices": 0.37,
    "Generosity": 0.233,
    "Perceptions.of.corruption": 0.033
  },
  {
    "Year": 2018,
    "Country": "Comoros",
    "Continent": "Africa",
    "Happiness.Rank": 142,
    "Happiness.scores": 3.973,
    "GDP": 0.274,
    "Social.support": 0.757,
    "Helathy.life.expectancy": 0.505,
    "Freedom.to.make.choices": 0.142,
    "Generosity": 0.275,
    "Perceptions.of.corruption": 0.078
  },
  {
    "Year": 2018,
    "Country": "Madagascar",
    "Continent": "Africa",
    "Happiness.Rank": 143,
    "Happiness.scores": 3.933,
    "GDP": 0.274,
    "Social.support": 0.916,
    "Helathy.life.expectancy": 0.555,
    "Freedom.to.make.choices": 0.148,
    "Generosity": 0.169,
    "Perceptions.of.corruption": 0.041
  },
  {
    "Year": 2018,
    "Country": "Lesotho",
    "Continent": "Africa",
    "Happiness.Rank": 144,
    "Happiness.scores": 3.802,
    "GDP": 0.489,
    "Social.support": 1.169,
    "Helathy.life.expectancy": 0.168,
    "Freedom.to.make.choices": 0.359,
    "Generosity": 0.107,
    "Perceptions.of.corruption": 0.093
  },
  {
    "Year": 2018,
    "Country": "Burundi",
    "Continent": "Africa",
    "Happiness.Rank": 145,
    "Happiness.scores": 3.775,
    "GDP": 0.046,
    "Social.support": 0.447,
    "Helathy.life.expectancy": 0.38,
    "Freedom.to.make.choices": 0.22,
    "Generosity": 0.176,
    "Perceptions.of.corruption": 0.18
  },
  {
    "Year": 2018,
    "Country": "Zimbabwe",
    "Continent": "Africa",
    "Happiness.Rank": 146,
    "Happiness.scores": 3.663,
    "GDP": 0.366,
    "Social.support": 1.114,
    "Helathy.life.expectancy": 0.433,
    "Freedom.to.make.choices": 0.361,
    "Generosity": 0.151,
    "Perceptions.of.corruption": 0.089
  },
  {
    "Year": 2018,
    "Country": "Botswana",
    "Continent": "Africa",
    "Happiness.Rank": 148,
    "Happiness.scores": 3.488,
    "GDP": 1.041,
    "Social.support": 1.145,
    "Helathy.life.expectancy": 0.538,
    "Freedom.to.make.choices": 0.455,
    "Generosity": 0.025,
    "Perceptions.of.corruption": 0.1
  },
  {
    "Year": 2018,
    "Country": "Malawi",
    "Continent": "Africa",
    "Happiness.Rank": 150,
    "Happiness.scores": 3.41,
    "GDP": 0.191,
    "Social.support": 0.56,
    "Helathy.life.expectancy": 0.495,
    "Freedom.to.make.choices": 0.443,
    "Generosity": 0.218,
    "Perceptions.of.corruption": 0.089
  },
  {
    "Year": 2018,
    "Country": "Rwanda",
    "Continent": "Africa",
    "Happiness.Rank": 152,
    "Happiness.scores": 3.334,
    "GDP": 0.359,
    "Social.support": 0.711,
    "Helathy.life.expectancy": 0.614,
    "Freedom.to.make.choices": 0.555,
    "Generosity": 0.217,
    "Perceptions.of.corruption": 0.411
  },
  {
    "Year": 2018,
    "Country": "Tanzania",
    "Continent": "Africa",
    "Happiness.Rank": 153,
    "Happiness.scores": 3.231,
    "GDP": 0.476,
    "Social.support": 0.885,
    "Helathy.life.expectancy": 0.499,
    "Freedom.to.make.choices": 0.417,
    "Generosity": 0.276,
    "Perceptions.of.corruption": 0.147
  },
  {
    "Year": 2018,
    "Country": "Central African Republic",
    "Continent": "Africa",
    "Happiness.Rank": 155,
    "Happiness.scores": 3.083,
    "GDP": 0.026,
    "Social.support": 0,
    "Helathy.life.expectancy": 0.105,
    "Freedom.to.make.choices": 0.225,
    "Generosity": 0.235,
    "Perceptions.of.corruption": 0.035
  },
  {
    "Year": 2018,
    "Country": "South Sudan",
    "Continent": "Africa",
    "Happiness.Rank": 156,
    "Happiness.scores": 2.853,
    "GDP": 0.306,
    "Social.support": 0.575,
    "Helathy.life.expectancy": 0.295,
    "Freedom.to.make.choices": 0.01,
    "Generosity": 0.202,
    "Perceptions.of.corruption": 0.091
  }
]